[
  {
    "chromosome": "1",
    "length": 248387328,
    "accession": "NC_060925.1"
  },
  {
    "chromosome": "2",
    "length": 242696752,
    "accession": "NC_060926.1"
  },
  {
    "chromosome": "3",
    "length": 201105948,
    "accession": "NC_060927.1"
  },
  {
    "chromosome": "4",
    "length": 193574945,
    "accession": "NC_060928.1"
  },
  {
    "chromosome": "5",
    "length": 182045439,
    "accession": "NC_060929.1"
  },
  {
    "chromosome": "6",
    "length": 172126628,
    "accession": "NC_060930.1"
  },
  {
    "chromosome": "7",
    "length": 160567428,
    "accession": "NC_060931.1"
  },
  {
    "chromosome": "8",
    "length": 146259331,
    "accession": "NC_060932.1"
  },
  {
    "chromosome": "9",
    "length": 150617247,
    "accession": "NC_060933.1"
  },
  {
    "chromosome": "10",
    "length": 134758134,
    "accession": "NC_060934.1"
  },
  {
    "chromosome": "11",
    "length": 135127769,
    "accession": "NC_060935.1"
  },
  {
    "chromosome": "12",
    "length": 133324548,
    "accession": "NC_060936.1"
  },
  {
    "chromosome": "13",
    "length": 113566686,
    "accession": "NC_060937.1"
  },
  {
    "chromosome": "14",
    "length": 101161492,
    "accession": "NC_060938.1"
  },
  {
    "chromosome": "15",
    "length": 99753195,
    "accession": "NC_060939.1"
  },
  {
    "chromosome": "16",
    "length": 96330374,
    "accession": "NC_060940.1"
  },
  {
    "chromosome": "17",
    "length": 84276897,
    "accession": "NC_060941.1"
  },
  {
    "chromosome": "18",
    "length": 80542538,
    "accession": "NC_060942.1"
  },
  {
    "chromosome": "19",
    "length": 61707364,
    "accession": "NC_060943.1"
  },
  {
    "chromosome": "20",
    "length": 66210255,
    "accession": "NC_060944.1"
  },
  {
    "chromosome": "21",
    "length": 45090682,
    "accession": "NC_060945.1"
  },
  {
    "chromosome": "22",
    "length": 51324926,
    "accession": "NC_060946.1"
  },
  {
    "chromosome": "X",
    "length": 154259566,
    "accession": "NC_060947.1"
  },
  {
    "chromosome": "Y",
    "length": 62460029,
    "accession": "NC_060948.1"
  }
]